uberdict/__init__.py
uberdict-0.4.3.dist-info/DESCRIPTION.rst
uberdict-0.4.3.dist-info/METADATA
uberdict-0.4.3.dist-info/RECORD
uberdict-0.4.3.dist-info/WHEEL
uberdict-0.4.3.dist-info/metadata.json
uberdict-0.4.3.dist-info/top_level.txt
